<xml version="1.0">
<dashboard>
	<widget field="Rear Left Distance" type="Number" class="edu.wpi.first.smartdashboard.gui.elements.TextBox">
		<location x="32" y="597"/>
	</widget>
	<widget field="Rear Right Distance" type="Number" class="edu.wpi.first.smartdashboard.gui.elements.TextBox">
		<location x="220" y="600"/>
	</widget>
	<widget field="Front Left Distance" type="Number" class="edu.wpi.first.smartdashboard.gui.elements.TextBox">
		<location x="25" y="571"/>
	</widget>
	<widget field="Front Right Distance" type="Number" class="edu.wpi.first.smartdashboard.gui.elements.TextBox">
		<location x="216" y="576"/>
	</widget>
	<widget field="Rear Left Speed" type="Number" class="edu.wpi.first.smartdashboard.gui.elements.TextBox">
		<location x="37" y="532"/>
	</widget>
	<widget field="Rear Right Speed" type="Number" class="edu.wpi.first.smartdashboard.gui.elements.TextBox">
		<location x="226" y="536"/>
	</widget>
	<widget field="Front Left Speed" type="Number" class="edu.wpi.first.smartdashboard.gui.elements.TextBox">
		<location x="33" y="509"/>
	</widget>
	<widget field="Front Right Speed" type="Number" class="edu.wpi.first.smartdashboard.gui.elements.TextBox">
		<location x="224" y="511"/>
	</widget>
	<widget field="Field Centricity" type="Boolean" class="edu.wpi.first.smartdashboard.gui.elements.TextBox">
		<location x="429" y="145"/>
	</widget>
	<widget field="Gyro Angle" type="Number" class="edu.wpi.first.smartdashboard.gui.elements.TextBox">
		<location x="59" y="307"/>
	</widget>
	<widget field="Debug" type="String" class="edu.wpi.first.smartdashboard.gui.elements.TextBox">
		<location x="318" y="187"/>
		<width>243</width>
	</widget>
	<widget field="DriveDistance: TwoMeters" type="Command" class="edu.wpi.first.smartdashboard.gui.elements.Command">
		<location x="384" y="84"/>
	</widget>
	<widget field="DriveDistance: OneMeter" type="Command" class="edu.wpi.first.smartdashboard.gui.elements.Command">
		<location x="390" y="51"/>
	</widget>
	<widget field="Autonomous Mode" type="String Chooser" class="edu.wpi.first.smartdashboard.gui.elements.Chooser">
		<location x="34" y="57"/>
	</widget>
	<widget field="Rear Right Angle" type="Number" class="edu.wpi.first.smartdashboard.gui.elements.TextBox">
		<location x="33" y="473"/>
	</widget>
	<widget field="Rear Right Drive" type="Number" class="edu.wpi.first.smartdashboard.gui.elements.TextBox">
		<location x="232" y="416"/>
		<height>20</height>
	</widget>
	<widget field="Rear Left Angle" type="Number" class="edu.wpi.first.smartdashboard.gui.elements.TextBox">
		<location x="237" y="472"/>
	</widget>
	<widget field="Rear Left Drive" type="Number" class="edu.wpi.first.smartdashboard.gui.elements.TextBox">
		<location x="39" y="414"/>
	</widget>
	<widget field="Front Left Angle" type="Number" class="edu.wpi.first.smartdashboard.gui.elements.TextBox">
		<location x="37" y="449"/>
	</widget>
	<widget field="Front Left Drive" type="Number" class="edu.wpi.first.smartdashboard.gui.elements.TextBox">
		<location x="39" y="391"/>
	</widget>
	<widget field="Front Right Angle" type="Number" class="edu.wpi.first.smartdashboard.gui.elements.TextBox">
		<location x="227" y="448"/>
		<height>20</height>
	</widget>
	<widget field="Front Right Drive" type="Number" class="edu.wpi.first.smartdashboard.gui.elements.TextBox">
		<location x="230" y="393"/>
	</widget>
	<widget field="Chassis Angle" type="Number" class="edu.wpi.first.smartdashboard.gui.elements.TextBox">
		<location x="46" y="282"/>
	</widget>
	<widget field="Chassis Strafe" type="Number" class="edu.wpi.first.smartdashboard.gui.elements.TextBox">
		<location x="46" y="258"/>
	</widget>
	<widget field="Chassis Forward" type="Number" class="edu.wpi.first.smartdashboard.gui.elements.TextBox">
		<location x="38" y="233"/>
	</widget>
	<widget field="pose_0" type="String" class="edu.wpi.first.smartdashboard.gui.elements.TextBox">
		<location x="589" y="450"/>
		<width>494</width>
	</widget>
	<widget field="April Tag Z: " type="Number" class="edu.wpi.first.smartdashboard.gui.elements.TextBox">
		<location x="588" y="529"/>
	</widget>
	<widget field="April Tag Y: " type="Number" class="edu.wpi.first.smartdashboard.gui.elements.TextBox">
		<location x="587" y="504"/>
	</widget>
	<widget field="April Tag X: " type="Number" class="edu.wpi.first.smartdashboard.gui.elements.TextBox">
		<location x="586" y="479"/>
	</widget>
	<static-widget class="edu.wpi.first.smartdashboard.gui.elements.CameraServerViewer">
		<location x="614" y="10"/>
		<width>515</width>
		<height>389</height>
		<property name="Camera Choice" value="Detected"/>
	</static-widget>
	<static-widget class="edu.wpi.first.smartdashboard.gui.elements.ConnectionIndicator">
		<location x="31" y="16"/>
		<width>193</width>
	</static-widget>
	<widget field="ChassisDrive: Stop" type="Command" class="edu.wpi.first.smartdashboard.gui.elements.Command">
		<location x="421" y="20"/>
	</widget>
	<widget field="tags" type="String" class="edu.wpi.first.smartdashboard.gui.elements.TextBox">
		<location x="748" y="424"/>
	</widget>
	<widget field="Detections: " type="Number" class="edu.wpi.first.smartdashboard.gui.elements.TextBox">
		<location x="588" y="423"/>
	</widget>
</dashboard>
<live-window>
	<widget field="Ungrouped" type="LW Subsystem" class="edu.wpi.first.smartdashboard.livewindow.elements.LWSubsystem">
		<widget field="Talon FX (v6) [3]" type="Motor Controller" class="edu.wpi.first.smartdashboard.livewindow.elements.SpeedController">
			<location x="6" y="16"/>
			<height>45</height>
			<width>293</width>
		</widget>
		<widget field="Talon FX (v6) [9]" type="Motor Controller" class="edu.wpi.first.smartdashboard.livewindow.elements.SpeedController">
			<location x="6" y="61"/>
			<height>45</height>
			<width>293</width>
		</widget>
		<widget field="frc2::SubsystemBase" type="Subsystem" class="edu.wpi.first.smartdashboard.gui.elements.Subsystem">
			<location x="6" y="106"/>
			<height>20</height>
			<width>293</width>
		</widget>
		<widget field="Scheduler" type="Scheduler" class="edu.wpi.first.smartdashboard.gui.elements.Scheduler">
			<location x="6" y="126"/>
			<height>14</height>
			<width>293</width>
		</widget>
		<widget field="Talon FX (v6) [6]" type="Motor Controller" class="edu.wpi.first.smartdashboard.livewindow.elements.SpeedController">
			<location x="6" y="140"/>
			<height>45</height>
			<width>293</width>
		</widget>
		<widget field="Talon FX (v6) [11]" type="Motor Controller" class="edu.wpi.first.smartdashboard.livewindow.elements.SpeedController">
			<location x="6" y="185"/>
			<height>45</height>
			<width>293</width>
		</widget>
		<widget field="navX-Sensor[4]" type="Gyro" class="edu.wpi.first.smartdashboard.gui.elements.Compass">
			<location x="6" y="230"/>
			<height>150</height>
			<width>293</width>
		</widget>
		<widget field="Talon FX (v6) [20]" type="Motor Controller" class="edu.wpi.first.smartdashboard.livewindow.elements.SpeedController">
			<location x="6" y="380"/>
			<height>45</height>
			<width>293</width>
		</widget>
		<location x="0" y="23"/>
		<width>305</width>
		<height>431</height>
	</widget>
	<widget field="AprilTags" type="LW Subsystem" class="edu.wpi.first.smartdashboard.livewindow.elements.LWSubsystem">
		<location x="0" y="0"/>
	</widget>
</live-window>
	<hidden field="Front Left correctedDesired Speed"/>
	<hidden field="Wheel State Speed"/>
	<hidden field="Rear Right correctedDesired Speed"/>
	<hidden field="Wheel Position Angle"/>
	<hidden field="SetWheelAngleToForward"/>
	<hidden field="Wheel Velocity"/>
	<hidden field="Wheel State Angle"/>
	<hidden field="Wheel Positoin Distance"/>
	<hidden field="Front Right correctedDesired Speed"/>
	<hidden field="Rear Left correctedDesired Speed"/>
	<hidden field="Wheel Position Distance"/>
	<hidden field="Wheel Position"/>
</xml>